rolepermissions/__init__.py
rolepermissions/admin.py
rolepermissions/apps.py
rolepermissions/checkers.py
rolepermissions/decorators.py
rolepermissions/exceptions.py
rolepermissions/loader.py
rolepermissions/mixins.py
rolepermissions/models.py
rolepermissions/permissions.py
rolepermissions/roles.py
rolepermissions/utils.py
rolepermissions/__pycache__/__init__.cpython-36.pyc
rolepermissions/__pycache__/admin.cpython-36.pyc
rolepermissions/__pycache__/apps.cpython-36.pyc
rolepermissions/__pycache__/checkers.cpython-36.pyc
rolepermissions/__pycache__/decorators.cpython-36.pyc
rolepermissions/__pycache__/exceptions.cpython-36.pyc
rolepermissions/__pycache__/loader.cpython-36.pyc
rolepermissions/__pycache__/mixins.cpython-36.pyc
rolepermissions/__pycache__/models.cpython-36.pyc
rolepermissions/__pycache__/permissions.cpython-36.pyc
rolepermissions/__pycache__/roles.cpython-36.pyc
rolepermissions/__pycache__/utils.cpython-36.pyc
rolepermissions/management/__init__.py
rolepermissions/management/__pycache__/__init__.cpython-36.pyc
rolepermissions/management/commands/__init__.py
rolepermissions/management/commands/sync_roles.py
rolepermissions/management/commands/__pycache__/__init__.cpython-36.pyc
rolepermissions/management/commands/__pycache__/sync_roles.cpython-36.pyc
rolepermissions/templatetags/__init__.py
rolepermissions/templatetags/permission_tags.py
rolepermissions/templatetags/__pycache__/__init__.cpython-36.pyc
rolepermissions/templatetags/__pycache__/permission_tags.cpython-36.pyc
rolepermissions/tests/__init__.py
rolepermissions/tests/mock_urls.py
rolepermissions/tests/test_admin.py
rolepermissions/tests/test_decorators.py
rolepermissions/tests/test_mixins.py
rolepermissions/tests/test_permissions.py
rolepermissions/tests/test_roles.py
rolepermissions/tests/test_shortcuts.py
rolepermissions/tests/test_template_tags.py
rolepermissions/tests/test_utils.py
rolepermissions/tests/test_verifications.py
rolepermissions/tests/__pycache__/__init__.cpython-36.pyc
django_role_permissions_pr95-2.2.1.dist-info/LICENSE
django_role_permissions_pr95-2.2.1.dist-info/METADATA
django_role_permissions_pr95-2.2.1.dist-info/WHEEL
django_role_permissions_pr95-2.2.1.dist-info/top_level.txt
django_role_permissions_pr95-2.2.1.dist-info/RECORD
