Metadata-Version: 2.1
Name: django-role-permissions-pr95
Version: 2.2.1
Summary: A django app for role based permissions.
Home-page: http://github.com/vintasoftware/django-role-permissions
Author: Filipe Ximenes
Author-email: filipeximenes@gmail.com
License: MIT
Platform: UNKNOWN
Classifier: Development Status :: 5 - Production/Stable
Classifier: Intended Audience :: Developers
Classifier: License :: OSI Approved :: MIT License
Classifier: Natural Language :: English
Classifier: Programming Language :: Python :: 2
Classifier: Programming Language :: Python :: 2.7
Classifier: Programming Language :: Python :: 3
Classifier: Programming Language :: Python :: 3.4
Classifier: Programming Language :: Python :: 3.5
Classifier: Programming Language :: Python :: 3.6
Requires-Dist: Django (>=1.5)
Requires-Dist: django-discover-runner
Requires-Dist: six
